setup.py
tuplespace.py
tuplespace.egg-info/PKG-INFO
tuplespace.egg-info/SOURCES.txt
tuplespace.egg-info/dependency_links.txt
tuplespace.egg-info/top_level.txt