Metadata-Version: 1.1
Name: tuplespace
Version: 0.1.0
Summary: Python client for a Tuple Space service.
Home-page: http://github.com/alecthomas/tuplespace
Author: Alec Thomas
Author-email: alec@swapoff.org
License: BSD
Download-URL: http://github.com/alecthomas/tuplespace
Platform: any
